po_lsp.py
po_language_server-0.0.2.dist-info/METADATA
po_language_server-0.0.2.dist-info/WHEEL
po_language_server-0.0.2.dist-info/entry_points.txt
po_language_server-0.0.2.dist-info/top_level.txt
po_language_server-0.0.2.dist-info/RECORD
