Metadata-Version: 2.1
Name: po-language-server
Version: 0.0.2
Summary: Language Server for gettext po files.
Home-page: UNKNOWN
Author: Julien Palard
Author-email: julien@palard.fr
License: MIT License
Platform: UNKNOWN
Classifier: License :: OSI Approved :: MIT License
Classifier: Programming Language :: Python :: 3
Requires-Python: >=3.6
Requires-Dist: pygls
